{
  "certificate": "lc",
  "subject": "physics",
  "level": "hl",
  "course": "old",
  "topics": [
    "Acceleration",
    "Applied Electricity",
    "Circular Motion",
    "Current & Charge",
    "Electric Circuits",
    "Electromagnetic Induction",
    "Exp. Qs (all)",
    "Exp. Qs. - Electricity",
    "Exp. Qs. - Heat",
    "Exp. Qs. - Light",
    "Exp. Qs. - Mechanics",
    "Exp. Qs. - Sound",
    "Force, Mass & Momentum",
    "Heat & Heat Transfer",
    "Light",
    "Magnets & Magnetic Fields",
    "Nuclear Energy",
    "Particle Physics",
    "Potential Difference & Capacitance",
    "Pressure, Gravity & Moments",
    "Reflection & Mirrors",
    "Refraction & Lenses",
    "Resistance",
    "Semiconductors",
    "Simple Harmonic Motion",
    "Speed, Displacement, Velocity",
    "Static Electricity",
    "Temperature & Thermometers",
    "The Atom, Nucleus & Radioactivity",
    "The Electron",
    "Vectors & Scalars",
    "Vibration & Sound",
    "Waves & Wave Motion",
    "Work, Energy & Power"
  ]
}